odoo9_addon_sale_rental-9.0.1.0.0-py2.7-nspkg.pth
odoo9_addon_sale_rental-9.0.1.0.0.dist-info/top_level.txt
odoo9_addon_sale_rental-9.0.1.0.0.dist-info/WHEEL
odoo9_addon_sale_rental-9.0.1.0.0.dist-info/RECORD
odoo9_addon_sale_rental-9.0.1.0.0.dist-info/metadata.json
odoo9_addon_sale_rental-9.0.1.0.0.dist-info/DESCRIPTION.rst
odoo9_addon_sale_rental-9.0.1.0.0.dist-info/METADATA
odoo9_addon_sale_rental-9.0.1.0.0.dist-info/namespace_packages.txt
odoo_addons/sale_rental/__openerp__.py
odoo_addons/sale_rental/__init__.py
odoo_addons/sale_rental/README.rst
odoo_addons/sale_rental/security/sale_rental_security.xml
odoo_addons/sale_rental/security/ir.model.access.csv
odoo_addons/sale_rental/models/stock.py
odoo_addons/sale_rental/models/product.py
odoo_addons/sale_rental/models/sale_rental.py
odoo_addons/sale_rental/models/sale_order.py
odoo_addons/sale_rental/models/__init__.py
odoo_addons/sale_rental/i18n/zh_CN.po
odoo_addons/sale_rental/i18n/sale_rental.pot
odoo_addons/sale_rental/i18n/it.po
odoo_addons/sale_rental/i18n/es.po
odoo_addons/sale_rental/i18n/sl.po
odoo_addons/sale_rental/i18n/de.po
odoo_addons/sale_rental/i18n/fr.po
odoo_addons/sale_rental/i18n/pt_BR.po
odoo_addons/sale_rental/i18n/fi.po
odoo_addons/sale_rental/wizard/__init__.py
odoo_addons/sale_rental/wizard/create_rental_product.py
odoo_addons/sale_rental/wizard/create_rental_product_view.xml
odoo_addons/sale_rental/views/sale_order.xml
odoo_addons/sale_rental/views/product.xml
odoo_addons/sale_rental/views/stock.xml
odoo_addons/sale_rental/views/sale_rental.xml
odoo_addons/sale_rental/data/rental_data.xml
odoo_addons/sale_rental/demo/rental_demo.xml
odoo_addons/sale_rental/static/description/icon.png
